d_cube/__init__.py
d_cube/d3.py
d_cube/data_util.py
d_cube/vis_util.py
ddd_dataset-0.1.2.dist-info/LICENSE
ddd_dataset-0.1.2.dist-info/METADATA
ddd_dataset-0.1.2.dist-info/WHEEL
ddd_dataset-0.1.2.dist-info/top_level.txt
ddd_dataset-0.1.2.dist-info/RECORD
