Metadata-Version: 2.1
Name: ddd-dataset
Version: 0.1.2
Summary: Toolkit for Description Detection Dataset ($D^3$)
Home-page: https://github.com/shikras/d-cube
Author: Chi Xie
Author-email: chixie.personal@gmail.com
License: CC BY-NC 4.0
Project-URL: Bug Tracker, https://github.com/shikras/d-cube/issues
Classifier: Development Status :: 4 - Beta
Classifier: Intended Audience :: Science/Research
Classifier: Intended Audience :: Developers
Classifier: Intended Audience :: Education
Classifier: Operating System :: MacOS
Classifier: Operating System :: Microsoft :: Windows
Classifier: Operating System :: POSIX :: Linux
Classifier: Programming Language :: Python :: 3
License-File: LICENSE
Requires-Dist: numpy
Requires-Dist: pycocotools
Requires-Dist: opencv-python
Requires-Dist: matplotlib
